<?xml version="1.0" encoding="UTF-8"?>
<?xml-stylesheet href="CoreNLP-to-HTML.xsl" type="text/xsl"?>
<root>
  <document>
    <sentences>
      <sentence id="1">
        <tokens>
          <token id="1">
            <word>http://www.zdnet.com/article/catching-light-in-a-graphene-net/#ftag=RSSbaffb68</word>
            <lemma>http://www.zdnet.com/article/catching-light-in-a-graphene-net/#ftag=rssbaffb68</lemma>
            <CharacterOffsetBegin>0</CharacterOffsetBegin>
            <CharacterOffsetEnd>78</CharacterOffsetEnd>
            <POS>NN</POS>
            <NER>O</NER>
          </token>
          <token id="2">
            <word>Catching</word>
            <lemma>catch</lemma>
            <CharacterOffsetBegin>79</CharacterOffsetBegin>
            <CharacterOffsetEnd>87</CharacterOffsetEnd>
            <POS>VBG</POS>
            <NER>O</NER>
          </token>
          <token id="3">
            <word>light</word>
            <lemma>light</lemma>
            <CharacterOffsetBegin>88</CharacterOffsetBegin>
            <CharacterOffsetEnd>93</CharacterOffsetEnd>
            <POS>NN</POS>
            <NER>O</NER>
          </token>
          <token id="4">
            <word>in</word>
            <lemma>in</lemma>
            <CharacterOffsetBegin>94</CharacterOffsetBegin>
            <CharacterOffsetEnd>96</CharacterOffsetEnd>
            <POS>IN</POS>
            <NER>O</NER>
          </token>
          <token id="5">
            <word>a</word>
            <lemma>a</lemma>
            <CharacterOffsetBegin>97</CharacterOffsetBegin>
            <CharacterOffsetEnd>98</CharacterOffsetEnd>
            <POS>DT</POS>
            <NER>O</NER>
          </token>
          <token id="6">
            <word>graphene</word>
            <lemma>graphene</lemma>
            <CharacterOffsetBegin>99</CharacterOffsetBegin>
            <CharacterOffsetEnd>107</CharacterOffsetEnd>
            <POS>NN</POS>
            <NER>O</NER>
          </token>
          <token id="7">
            <word>net</word>
            <lemma>net</lemma>
            <CharacterOffsetBegin>108</CharacterOffsetBegin>
            <CharacterOffsetEnd>111</CharacterOffsetEnd>
            <POS>JJ</POS>
            <NER>O</NER>
          </token>
          <token id="8">
            <word>An</word>
            <lemma>a</lemma>
            <CharacterOffsetBegin>112</CharacterOffsetBegin>
            <CharacterOffsetEnd>114</CharacterOffsetEnd>
            <POS>DT</POS>
            <NER>O</NER>
          </token>
          <token id="9">
            <word>international</word>
            <lemma>international</lemma>
            <CharacterOffsetBegin>115</CharacterOffsetBegin>
            <CharacterOffsetEnd>128</CharacterOffsetEnd>
            <POS>JJ</POS>
            <NER>O</NER>
          </token>
          <token id="10">
            <word>team</word>
            <lemma>team</lemma>
            <CharacterOffsetBegin>129</CharacterOffsetBegin>
            <CharacterOffsetEnd>133</CharacterOffsetEnd>
            <POS>NN</POS>
            <NER>O</NER>
          </token>
          <token id="11">
            <word>of</word>
            <lemma>of</lemma>
            <CharacterOffsetBegin>134</CharacterOffsetBegin>
            <CharacterOffsetEnd>136</CharacterOffsetEnd>
            <POS>IN</POS>
            <NER>O</NER>
          </token>
          <token id="12">
            <word>physicists</word>
            <lemma>physicist</lemma>
            <CharacterOffsetBegin>137</CharacterOffsetBegin>
            <CharacterOffsetEnd>147</CharacterOffsetEnd>
            <POS>NNS</POS>
            <NER>O</NER>
          </token>
          <token id="13">
            <word>led</word>
            <lemma>lead</lemma>
            <CharacterOffsetBegin>148</CharacterOffsetBegin>
            <CharacterOffsetEnd>151</CharacterOffsetEnd>
            <POS>VBN</POS>
            <NER>O</NER>
          </token>
          <token id="14">
            <word>by</word>
            <lemma>by</lemma>
            <CharacterOffsetBegin>152</CharacterOffsetBegin>
            <CharacterOffsetEnd>154</CharacterOffsetEnd>
            <POS>IN</POS>
            <NER>O</NER>
          </token>
          <token id="15">
            <word>US</word>
            <lemma>US</lemma>
            <CharacterOffsetBegin>155</CharacterOffsetBegin>
            <CharacterOffsetEnd>157</CharacterOffsetEnd>
            <POS>NNP</POS>
            <NER>LOCATION</NER>
          </token>
          <token id="16">
            <word>researcher</word>
            <lemma>researcher</lemma>
            <CharacterOffsetBegin>158</CharacterOffsetBegin>
            <CharacterOffsetEnd>168</CharacterOffsetEnd>
            <POS>NN</POS>
            <NER>O</NER>
          </token>
          <token id="17">
            <word>Dmitri</word>
            <lemma>Dmitri</lemma>
            <CharacterOffsetBegin>169</CharacterOffsetBegin>
            <CharacterOffsetEnd>175</CharacterOffsetEnd>
            <POS>NNP</POS>
            <NER>PERSON</NER>
          </token>
          <token id="18">
            <word>Basov</word>
            <lemma>Basov</lemma>
            <CharacterOffsetBegin>176</CharacterOffsetBegin>
            <CharacterOffsetEnd>181</CharacterOffsetEnd>
            <POS>NNP</POS>
            <NER>PERSON</NER>
          </token>
          <token id="19">
            <word>,</word>
            <lemma>,</lemma>
            <CharacterOffsetBegin>181</CharacterOffsetBegin>
            <CharacterOffsetEnd>182</CharacterOffsetEnd>
            <POS>,</POS>
            <NER>O</NER>
          </token>
          <token id="20">
            <word>of</word>
            <lemma>of</lemma>
            <CharacterOffsetBegin>183</CharacterOffsetBegin>
            <CharacterOffsetEnd>185</CharacterOffsetEnd>
            <POS>IN</POS>
            <NER>O</NER>
          </token>
          <token id="21">
            <word>the</word>
            <lemma>the</lemma>
            <CharacterOffsetBegin>186</CharacterOffsetBegin>
            <CharacterOffsetEnd>189</CharacterOffsetEnd>
            <POS>DT</POS>
            <NER>O</NER>
          </token>
          <token id="22">
            <word>University</word>
            <lemma>University</lemma>
            <CharacterOffsetBegin>190</CharacterOffsetBegin>
            <CharacterOffsetEnd>200</CharacterOffsetEnd>
            <POS>NNP</POS>
            <NER>ORGANIZATION</NER>
          </token>
          <token id="23">
            <word>of</word>
            <lemma>of</lemma>
            <CharacterOffsetBegin>201</CharacterOffsetBegin>
            <CharacterOffsetEnd>203</CharacterOffsetEnd>
            <POS>IN</POS>
            <NER>ORGANIZATION</NER>
          </token>
          <token id="24">
            <word>California</word>
            <lemma>California</lemma>
            <CharacterOffsetBegin>204</CharacterOffsetBegin>
            <CharacterOffsetEnd>214</CharacterOffsetEnd>
            <POS>NNP</POS>
            <NER>ORGANIZATION</NER>
          </token>
          <token id="25">
            <word>,</word>
            <lemma>,</lemma>
            <CharacterOffsetBegin>214</CharacterOffsetBegin>
            <CharacterOffsetEnd>215</CharacterOffsetEnd>
            <POS>,</POS>
            <NER>O</NER>
          </token>
          <token id="26">
            <word>demonstrated</word>
            <lemma>demonstrate</lemma>
            <CharacterOffsetBegin>216</CharacterOffsetBegin>
            <CharacterOffsetEnd>228</CharacterOffsetEnd>
            <POS>VBD</POS>
            <NER>O</NER>
          </token>
          <token id="27">
            <word>that</word>
            <lemma>that</lemma>
            <CharacterOffsetBegin>229</CharacterOffsetBegin>
            <CharacterOffsetEnd>233</CharacterOffsetEnd>
            <POS>IN</POS>
            <NER>O</NER>
          </token>
          <token id="28">
            <word>light</word>
            <lemma>light</lemma>
            <CharacterOffsetBegin>234</CharacterOffsetBegin>
            <CharacterOffsetEnd>239</CharacterOffsetEnd>
            <POS>NN</POS>
            <NER>O</NER>
          </token>
          <token id="29">
            <word>can</word>
            <lemma>can</lemma>
            <CharacterOffsetBegin>240</CharacterOffsetBegin>
            <CharacterOffsetEnd>243</CharacterOffsetEnd>
            <POS>MD</POS>
            <NER>O</NER>
          </token>
          <token id="30">
            <word>be</word>
            <lemma>be</lemma>
            <CharacterOffsetBegin>244</CharacterOffsetBegin>
            <CharacterOffsetEnd>246</CharacterOffsetEnd>
            <POS>VB</POS>
            <NER>O</NER>
          </token>
          <token id="31">
            <word>caught</word>
            <lemma>catch</lemma>
            <CharacterOffsetBegin>247</CharacterOffsetBegin>
            <CharacterOffsetEnd>253</CharacterOffsetEnd>
            <POS>VBN</POS>
            <NER>O</NER>
          </token>
          <token id="32">
            <word>and</word>
            <lemma>and</lemma>
            <CharacterOffsetBegin>254</CharacterOffsetBegin>
            <CharacterOffsetEnd>257</CharacterOffsetEnd>
            <POS>CC</POS>
            <NER>O</NER>
          </token>
          <token id="33">
            <word>controlled</word>
            <lemma>control</lemma>
            <CharacterOffsetBegin>258</CharacterOffsetBegin>
            <CharacterOffsetEnd>268</CharacterOffsetEnd>
            <POS>VBN</POS>
            <NER>O</NER>
          </token>
          <token id="34">
            <word>within</word>
            <lemma>within</lemma>
            <CharacterOffsetBegin>269</CharacterOffsetBegin>
            <CharacterOffsetEnd>275</CharacterOffsetEnd>
            <POS>IN</POS>
            <NER>O</NER>
          </token>
          <token id="35">
            <word>the</word>
            <lemma>the</lemma>
            <CharacterOffsetBegin>276</CharacterOffsetBegin>
            <CharacterOffsetEnd>279</CharacterOffsetEnd>
            <POS>DT</POS>
            <NER>O</NER>
          </token>
          <token id="36">
            <word>two</word>
            <lemma>two</lemma>
            <CharacterOffsetBegin>280</CharacterOffsetBegin>
            <CharacterOffsetEnd>283</CharacterOffsetEnd>
            <POS>CD</POS>
            <NER>NUMBER</NER>
            <NormalizedNER>2.0</NormalizedNER>
          </token>
          <token id="37">
            <word>dimensional</word>
            <lemma>dimensional</lemma>
            <CharacterOffsetBegin>284</CharacterOffsetBegin>
            <CharacterOffsetEnd>295</CharacterOffsetEnd>
            <POS>JJ</POS>
            <NER>O</NER>
          </token>
          <token id="38">
            <word>lattice</word>
            <lemma>lattice</lemma>
            <CharacterOffsetBegin>296</CharacterOffsetBegin>
            <CharacterOffsetEnd>303</CharacterOffsetEnd>
            <POS>NN</POS>
            <NER>O</NER>
          </token>
          <token id="39">
            <word>of</word>
            <lemma>of</lemma>
            <CharacterOffsetBegin>304</CharacterOffsetBegin>
            <CharacterOffsetEnd>306</CharacterOffsetEnd>
            <POS>IN</POS>
            <NER>O</NER>
          </token>
          <token id="40">
            <word>wonder-material</word>
            <lemma>wonder-material</lemma>
            <CharacterOffsetBegin>307</CharacterOffsetBegin>
            <CharacterOffsetEnd>322</CharacterOffsetEnd>
            <POS>JJ</POS>
            <NER>O</NER>
          </token>
          <token id="41">
            <word>graphene</word>
            <lemma>graphene</lemma>
            <CharacterOffsetBegin>323</CharacterOffsetBegin>
            <CharacterOffsetEnd>331</CharacterOffsetEnd>
            <POS>NN</POS>
            <NER>O</NER>
          </token>
          <token id="42">
            <word>.</word>
            <lemma>.</lemma>
            <CharacterOffsetBegin>331</CharacterOffsetBegin>
            <CharacterOffsetEnd>332</CharacterOffsetEnd>
            <POS>.</POS>
            <NER>O</NER>
          </token>
        </tokens>
      </sentence>
      <sentence id="2">
        <tokens>
          <token id="1">
            <word>Theory</word>
            <lemma>Theory</lemma>
            <CharacterOffsetBegin>333</CharacterOffsetBegin>
            <CharacterOffsetEnd>339</CharacterOffsetEnd>
            <POS>NNP</POS>
            <NER>O</NER>
          </token>
          <token id="2">
            <word>has</word>
            <lemma>have</lemma>
            <CharacterOffsetBegin>340</CharacterOffsetBegin>
            <CharacterOffsetEnd>343</CharacterOffsetEnd>
            <POS>VBZ</POS>
            <NER>O</NER>
          </token>
          <token id="3">
            <word>suggested</word>
            <lemma>suggest</lemma>
            <CharacterOffsetBegin>344</CharacterOffsetBegin>
            <CharacterOffsetEnd>353</CharacterOffsetEnd>
            <POS>VBN</POS>
            <NER>O</NER>
          </token>
          <token id="4">
            <word>that</word>
            <lemma>that</lemma>
            <CharacterOffsetBegin>354</CharacterOffsetBegin>
            <CharacterOffsetEnd>358</CharacterOffsetEnd>
            <POS>IN</POS>
            <NER>O</NER>
          </token>
          <token id="5">
            <word>long</word>
            <lemma>long</lemma>
            <CharacterOffsetBegin>359</CharacterOffsetBegin>
            <CharacterOffsetEnd>363</CharacterOffsetEnd>
            <POS>JJ</POS>
            <NER>O</NER>
          </token>
          <token id="6">
            <word>wavelength</word>
            <lemma>wavelength</lemma>
            <CharacterOffsetBegin>364</CharacterOffsetBegin>
            <CharacterOffsetEnd>374</CharacterOffsetEnd>
            <POS>NN</POS>
            <NER>O</NER>
          </token>
          <token id="7">
            <word>--</word>
            <lemma>--</lemma>
            <CharacterOffsetBegin>375</CharacterOffsetBegin>
            <CharacterOffsetEnd>376</CharacterOffsetEnd>
            <POS>:</POS>
            <NER>O</NER>
          </token>
          <token id="8">
            <word>infrared</word>
            <lemma>infrare</lemma>
            <CharacterOffsetBegin>377</CharacterOffsetBegin>
            <CharacterOffsetEnd>385</CharacterOffsetEnd>
            <POS>VBN</POS>
            <NER>O</NER>
          </token>
          <token id="9">
            <word>--</word>
            <lemma>--</lemma>
            <CharacterOffsetBegin>386</CharacterOffsetBegin>
            <CharacterOffsetEnd>387</CharacterOffsetEnd>
            <POS>:</POS>
            <NER>O</NER>
          </token>
          <token id="10">
            <word>photons</word>
            <lemma>photon</lemma>
            <CharacterOffsetBegin>388</CharacterOffsetBegin>
            <CharacterOffsetEnd>395</CharacterOffsetEnd>
            <POS>NNS</POS>
            <NER>O</NER>
          </token>
          <token id="11">
            <word>could</word>
            <lemma>could</lemma>
            <CharacterOffsetBegin>396</CharacterOffsetBegin>
            <CharacterOffsetEnd>401</CharacterOffsetEnd>
            <POS>MD</POS>
            <NER>O</NER>
          </token>
          <token id="12">
            <word>be</word>
            <lemma>be</lemma>
            <CharacterOffsetBegin>402</CharacterOffsetBegin>
            <CharacterOffsetEnd>404</CharacterOffsetEnd>
            <POS>VB</POS>
            <NER>O</NER>
          </token>
          <token id="13">
            <word>caught</word>
            <lemma>catch</lemma>
            <CharacterOffsetBegin>405</CharacterOffsetBegin>
            <CharacterOffsetEnd>411</CharacterOffsetEnd>
            <POS>VBN</POS>
            <NER>O</NER>
          </token>
          <token id="14">
            <word>and</word>
            <lemma>and</lemma>
            <CharacterOffsetBegin>412</CharacterOffsetBegin>
            <CharacterOffsetEnd>415</CharacterOffsetEnd>
            <POS>CC</POS>
            <NER>O</NER>
          </token>
          <token id="15">
            <word>moved</word>
            <lemma>move</lemma>
            <CharacterOffsetBegin>416</CharacterOffsetBegin>
            <CharacterOffsetEnd>421</CharacterOffsetEnd>
            <POS>VBN</POS>
            <NER>O</NER>
          </token>
          <token id="16">
            <word>through</word>
            <lemma>through</lemma>
            <CharacterOffsetBegin>422</CharacterOffsetBegin>
            <CharacterOffsetEnd>429</CharacterOffsetEnd>
            <POS>IN</POS>
            <NER>O</NER>
          </token>
          <token id="17">
            <word>graphene</word>
            <lemma>graphene</lemma>
            <CharacterOffsetBegin>430</CharacterOffsetBegin>
            <CharacterOffsetEnd>438</CharacterOffsetEnd>
            <POS>NN</POS>
            <NER>O</NER>
          </token>
          <token id="18">
            <word>at</word>
            <lemma>at</lemma>
            <CharacterOffsetBegin>439</CharacterOffsetBegin>
            <CharacterOffsetEnd>441</CharacterOffsetEnd>
            <POS>IN</POS>
            <NER>O</NER>
          </token>
          <token id="19">
            <word>much</word>
            <lemma>much</lemma>
            <CharacterOffsetBegin>442</CharacterOffsetBegin>
            <CharacterOffsetEnd>446</CharacterOffsetEnd>
            <POS>RB</POS>
            <NER>O</NER>
          </token>
          <token id="20">
            <word>less</word>
            <lemma>less</lemma>
            <CharacterOffsetBegin>447</CharacterOffsetBegin>
            <CharacterOffsetEnd>451</CharacterOffsetEnd>
            <POS>JJR</POS>
            <NER>O</NER>
          </token>
          <token id="21">
            <word>than</word>
            <lemma>than</lemma>
            <CharacterOffsetBegin>452</CharacterOffsetBegin>
            <CharacterOffsetEnd>456</CharacterOffsetEnd>
            <POS>IN</POS>
            <NER>O</NER>
          </token>
          <token id="22">
            <word>the</word>
            <lemma>the</lemma>
            <CharacterOffsetBegin>457</CharacterOffsetBegin>
            <CharacterOffsetEnd>460</CharacterOffsetEnd>
            <POS>DT</POS>
            <NER>O</NER>
          </token>
          <token id="23">
            <word>velocity</word>
            <lemma>velocity</lemma>
            <CharacterOffsetBegin>461</CharacterOffsetBegin>
            <CharacterOffsetEnd>469</CharacterOffsetEnd>
            <POS>NN</POS>
            <NER>O</NER>
          </token>
          <token id="24">
            <word>of</word>
            <lemma>of</lemma>
            <CharacterOffsetBegin>470</CharacterOffsetBegin>
            <CharacterOffsetEnd>472</CharacterOffsetEnd>
            <POS>IN</POS>
            <NER>O</NER>
          </token>
          <token id="25">
            <word>light</word>
            <lemma>light</lemma>
            <CharacterOffsetBegin>473</CharacterOffsetBegin>
            <CharacterOffsetEnd>478</CharacterOffsetEnd>
            <POS>NN</POS>
            <NER>O</NER>
          </token>
          <token id="26">
            <word>.</word>
            <lemma>.</lemma>
            <CharacterOffsetBegin>478</CharacterOffsetBegin>
            <CharacterOffsetEnd>479</CharacterOffsetEnd>
            <POS>.</POS>
            <NER>O</NER>
          </token>
        </tokens>
      </sentence>
      <sentence id="3">
        <tokens>
          <token id="1">
            <word>The</word>
            <lemma>the</lemma>
            <CharacterOffsetBegin>480</CharacterOffsetBegin>
            <CharacterOffsetEnd>483</CharacterOffsetEnd>
            <POS>DT</POS>
            <NER>O</NER>
          </token>
          <token id="2">
            <word>photons</word>
            <lemma>photon</lemma>
            <CharacterOffsetBegin>484</CharacterOffsetBegin>
            <CharacterOffsetEnd>491</CharacterOffsetEnd>
            <POS>NNS</POS>
            <NER>O</NER>
          </token>
          <token id="3">
            <word>were</word>
            <lemma>be</lemma>
            <CharacterOffsetBegin>492</CharacterOffsetBegin>
            <CharacterOffsetEnd>496</CharacterOffsetEnd>
            <POS>VBD</POS>
            <NER>O</NER>
          </token>
          <token id="4">
            <word>expected</word>
            <lemma>expect</lemma>
            <CharacterOffsetBegin>497</CharacterOffsetBegin>
            <CharacterOffsetEnd>505</CharacterOffsetEnd>
            <POS>VBN</POS>
            <NER>O</NER>
          </token>
          <token id="5">
            <word>to</word>
            <lemma>to</lemma>
            <CharacterOffsetBegin>506</CharacterOffsetBegin>
            <CharacterOffsetEnd>508</CharacterOffsetEnd>
            <POS>TO</POS>
            <NER>O</NER>
          </token>
          <token id="6">
            <word>be</word>
            <lemma>be</lemma>
            <CharacterOffsetBegin>509</CharacterOffsetBegin>
            <CharacterOffsetEnd>511</CharacterOffsetEnd>
            <POS>VB</POS>
            <NER>O</NER>
          </token>
          <token id="7">
            <word>slowed</word>
            <lemma>slow</lemma>
            <CharacterOffsetBegin>512</CharacterOffsetBegin>
            <CharacterOffsetEnd>518</CharacterOffsetEnd>
            <POS>VBN</POS>
            <NER>O</NER>
          </token>
          <token id="8">
            <word>down</word>
            <lemma>down</lemma>
            <CharacterOffsetBegin>519</CharacterOffsetBegin>
            <CharacterOffsetEnd>523</CharacterOffsetEnd>
            <POS>RP</POS>
            <NER>O</NER>
          </token>
          <token id="9">
            <word>by</word>
            <lemma>by</lemma>
            <CharacterOffsetBegin>524</CharacterOffsetBegin>
            <CharacterOffsetEnd>526</CharacterOffsetEnd>
            <POS>IN</POS>
            <NER>O</NER>
          </token>
          <token id="10">
            <word>their</word>
            <lemma>they</lemma>
            <CharacterOffsetBegin>527</CharacterOffsetBegin>
            <CharacterOffsetEnd>532</CharacterOffsetEnd>
            <POS>PRP$</POS>
            <NER>O</NER>
          </token>
          <token id="11">
            <word>interactions</word>
            <lemma>interaction</lemma>
            <CharacterOffsetBegin>533</CharacterOffsetBegin>
            <CharacterOffsetEnd>545</CharacterOffsetEnd>
            <POS>NNS</POS>
            <NER>O</NER>
          </token>
          <token id="12">
            <word>with</word>
            <lemma>with</lemma>
            <CharacterOffsetBegin>546</CharacterOffsetBegin>
            <CharacterOffsetEnd>550</CharacterOffsetEnd>
            <POS>IN</POS>
            <NER>O</NER>
          </token>
          <token id="13">
            <word>excited</word>
            <lemma>excited</lemma>
            <CharacterOffsetBegin>551</CharacterOffsetBegin>
            <CharacterOffsetEnd>558</CharacterOffsetEnd>
            <POS>JJ</POS>
            <NER>O</NER>
          </token>
          <token id="14">
            <word>electrons</word>
            <lemma>electron</lemma>
            <CharacterOffsetBegin>559</CharacterOffsetBegin>
            <CharacterOffsetEnd>568</CharacterOffsetEnd>
            <POS>NNS</POS>
            <NER>O</NER>
          </token>
          <token id="15">
            <word>in</word>
            <lemma>in</lemma>
            <CharacterOffsetBegin>569</CharacterOffsetBegin>
            <CharacterOffsetEnd>571</CharacterOffsetEnd>
            <POS>IN</POS>
            <NER>O</NER>
          </token>
          <token id="16">
            <word>the</word>
            <lemma>the</lemma>
            <CharacterOffsetBegin>572</CharacterOffsetBegin>
            <CharacterOffsetEnd>575</CharacterOffsetEnd>
            <POS>DT</POS>
            <NER>O</NER>
          </token>
          <token id="17">
            <word>graphene</word>
            <lemma>graphene</lemma>
            <CharacterOffsetBegin>576</CharacterOffsetBegin>
            <CharacterOffsetEnd>584</CharacterOffsetEnd>
            <POS>NN</POS>
            <NER>O</NER>
          </token>
          <token id="18">
            <word>structure</word>
            <lemma>structure</lemma>
            <CharacterOffsetBegin>585</CharacterOffsetBegin>
            <CharacterOffsetEnd>594</CharacterOffsetEnd>
            <POS>NN</POS>
            <NER>O</NER>
          </token>
          <token id="19">
            <word>,</word>
            <lemma>,</lemma>
            <CharacterOffsetBegin>594</CharacterOffsetBegin>
            <CharacterOffsetEnd>595</CharacterOffsetEnd>
            <POS>,</POS>
            <NER>O</NER>
          </token>
          <token id="20">
            <word>producing</word>
            <lemma>produce</lemma>
            <CharacterOffsetBegin>596</CharacterOffsetBegin>
            <CharacterOffsetEnd>605</CharacterOffsetEnd>
            <POS>VBG</POS>
            <NER>O</NER>
          </token>
          <token id="21">
            <word>a</word>
            <lemma>a</lemma>
            <CharacterOffsetBegin>606</CharacterOffsetBegin>
            <CharacterOffsetEnd>607</CharacterOffsetEnd>
            <POS>DT</POS>
            <NER>O</NER>
          </token>
          <token id="22">
            <word>hybrid</word>
            <lemma>hybrid</lemma>
            <CharacterOffsetBegin>608</CharacterOffsetBegin>
            <CharacterOffsetEnd>614</CharacterOffsetEnd>
            <POS>NN</POS>
            <NER>O</NER>
          </token>
          <token id="23">
            <word>particle</word>
            <lemma>particle</lemma>
            <CharacterOffsetBegin>615</CharacterOffsetBegin>
            <CharacterOffsetEnd>623</CharacterOffsetEnd>
            <POS>NN</POS>
            <NER>O</NER>
          </token>
          <token id="24">
            <word>known</word>
            <lemma>know</lemma>
            <CharacterOffsetBegin>624</CharacterOffsetBegin>
            <CharacterOffsetEnd>629</CharacterOffsetEnd>
            <POS>VBN</POS>
            <NER>O</NER>
          </token>
          <token id="25">
            <word>as</word>
            <lemma>as</lemma>
            <CharacterOffsetBegin>630</CharacterOffsetBegin>
            <CharacterOffsetEnd>632</CharacterOffsetEnd>
            <POS>IN</POS>
            <NER>O</NER>
          </token>
          <token id="26">
            <word>a</word>
            <lemma>a</lemma>
            <CharacterOffsetBegin>633</CharacterOffsetBegin>
            <CharacterOffsetEnd>634</CharacterOffsetEnd>
            <POS>DT</POS>
            <NER>O</NER>
          </token>
          <token id="27">
            <word>plasmon</word>
            <lemma>plasmon</lemma>
            <CharacterOffsetBegin>635</CharacterOffsetBegin>
            <CharacterOffsetEnd>642</CharacterOffsetEnd>
            <POS>NN</POS>
            <NER>O</NER>
          </token>
          <token id="28">
            <word>.</word>
            <lemma>.</lemma>
            <CharacterOffsetBegin>642</CharacterOffsetBegin>
            <CharacterOffsetEnd>643</CharacterOffsetEnd>
            <POS>.</POS>
            <NER>O</NER>
          </token>
        </tokens>
      </sentence>
      <sentence id="4">
        <tokens>
          <token id="1">
            <word>Until</word>
            <lemma>until</lemma>
            <CharacterOffsetBegin>644</CharacterOffsetBegin>
            <CharacterOffsetEnd>649</CharacterOffsetEnd>
            <POS>IN</POS>
            <NER>O</NER>
          </token>
          <token id="2">
            <word>now</word>
            <lemma>now</lemma>
            <CharacterOffsetBegin>650</CharacterOffsetBegin>
            <CharacterOffsetEnd>653</CharacterOffsetEnd>
            <POS>RB</POS>
            <NER>DATE</NER>
            <NormalizedNER>PRESENT_REF</NormalizedNER>
            <Timex tid="t1" type="DATE">PRESENT_REF</Timex>
          </token>
          <token id="3">
            <word>,</word>
            <lemma>,</lemma>
            <CharacterOffsetBegin>653</CharacterOffsetBegin>
            <CharacterOffsetEnd>654</CharacterOffsetEnd>
            <POS>,</POS>
            <NER>O</NER>
          </token>
          <token id="4">
            <word>researchers</word>
            <lemma>researcher</lemma>
            <CharacterOffsetBegin>655</CharacterOffsetBegin>
            <CharacterOffsetEnd>666</CharacterOffsetEnd>
            <POS>NNS</POS>
            <NER>O</NER>
          </token>
          <token id="5">
            <word>have</word>
            <lemma>have</lemma>
            <CharacterOffsetBegin>667</CharacterOffsetBegin>
            <CharacterOffsetEnd>671</CharacterOffsetEnd>
            <POS>VBP</POS>
            <NER>O</NER>
          </token>
          <token id="6">
            <word>been</word>
            <lemma>be</lemma>
            <CharacterOffsetBegin>672</CharacterOffsetBegin>
            <CharacterOffsetEnd>676</CharacterOffsetEnd>
            <POS>VBN</POS>
            <NER>O</NER>
          </token>
          <token id="7">
            <word>unable</word>
            <lemma>unable</lemma>
            <CharacterOffsetBegin>677</CharacterOffsetBegin>
            <CharacterOffsetEnd>683</CharacterOffsetEnd>
            <POS>JJ</POS>
            <NER>O</NER>
          </token>
          <token id="8">
            <word>to</word>
            <lemma>to</lemma>
            <CharacterOffsetBegin>684</CharacterOffsetBegin>
            <CharacterOffsetEnd>686</CharacterOffsetEnd>
            <POS>TO</POS>
            <NER>O</NER>
          </token>
          <token id="9">
            <word>study</word>
            <lemma>study</lemma>
            <CharacterOffsetBegin>687</CharacterOffsetBegin>
            <CharacterOffsetEnd>692</CharacterOffsetEnd>
            <POS>VB</POS>
            <NER>O</NER>
          </token>
          <token id="10">
            <word>the</word>
            <lemma>the</lemma>
            <CharacterOffsetBegin>693</CharacterOffsetBegin>
            <CharacterOffsetEnd>696</CharacterOffsetEnd>
            <POS>DT</POS>
            <NER>O</NER>
          </token>
          <token id="11">
            <word>plasmons</word>
            <lemma>plasmon</lemma>
            <CharacterOffsetBegin>697</CharacterOffsetBegin>
            <CharacterOffsetEnd>705</CharacterOffsetEnd>
            <POS>NNS</POS>
            <NER>O</NER>
          </token>
          <token id="12">
            <word>experimentally</word>
            <lemma>experimentally</lemma>
            <CharacterOffsetBegin>706</CharacterOffsetBegin>
            <CharacterOffsetEnd>720</CharacterOffsetEnd>
            <POS>RB</POS>
            <NER>O</NER>
          </token>
          <token id="13">
            <word>,</word>
            <lemma>,</lemma>
            <CharacterOffsetBegin>720</CharacterOffsetBegin>
            <CharacterOffsetEnd>721</CharacterOffsetEnd>
            <POS>,</POS>
            <NER>O</NER>
          </token>
          <token id="14">
            <word>because</word>
            <lemma>because</lemma>
            <CharacterOffsetBegin>722</CharacterOffsetBegin>
            <CharacterOffsetEnd>729</CharacterOffsetEnd>
            <POS>IN</POS>
            <NER>O</NER>
          </token>
          <token id="15">
            <word>the</word>
            <lemma>the</lemma>
            <CharacterOffsetBegin>730</CharacterOffsetBegin>
            <CharacterOffsetEnd>733</CharacterOffsetEnd>
            <POS>DT</POS>
            <NER>O</NER>
          </token>
          <token id="16">
            <word>IR</word>
            <lemma>IR</lemma>
            <CharacterOffsetBegin>734</CharacterOffsetBegin>
            <CharacterOffsetEnd>736</CharacterOffsetEnd>
            <POS>NNP</POS>
            <NER>O</NER>
          </token>
          <token id="17">
            <word>photons</word>
            <lemma>photon</lemma>
            <CharacterOffsetBegin>737</CharacterOffsetBegin>
            <CharacterOffsetEnd>744</CharacterOffsetEnd>
            <POS>NNS</POS>
            <NER>O</NER>
          </token>
          <token id="18">
            <word>did</word>
            <lemma>do</lemma>
            <CharacterOffsetBegin>745</CharacterOffsetBegin>
            <CharacterOffsetEnd>748</CharacterOffsetEnd>
            <POS>VBD</POS>
            <NER>O</NER>
          </token>
          <token id="19">
            <word>n't</word>
            <lemma>not</lemma>
            <CharacterOffsetBegin>748</CharacterOffsetBegin>
            <CharacterOffsetEnd>751</CharacterOffsetEnd>
            <POS>RB</POS>
            <NER>O</NER>
          </token>
          <token id="20">
            <word>have</word>
            <lemma>have</lemma>
            <CharacterOffsetBegin>752</CharacterOffsetBegin>
            <CharacterOffsetEnd>756</CharacterOffsetEnd>
            <POS>VB</POS>
            <NER>O</NER>
          </token>
          <token id="21">
            <word>enough</word>
            <lemma>enough</lemma>
            <CharacterOffsetBegin>757</CharacterOffsetBegin>
            <CharacterOffsetEnd>763</CharacterOffsetEnd>
            <POS>JJ</POS>
            <NER>O</NER>
          </token>
          <token id="22">
            <word>energy</word>
            <lemma>energy</lemma>
            <CharacterOffsetBegin>764</CharacterOffsetBegin>
            <CharacterOffsetEnd>770</CharacterOffsetEnd>
            <POS>NN</POS>
            <NER>O</NER>
          </token>
          <token id="23">
            <word>to</word>
            <lemma>to</lemma>
            <CharacterOffsetBegin>771</CharacterOffsetBegin>
            <CharacterOffsetEnd>773</CharacterOffsetEnd>
            <POS>TO</POS>
            <NER>O</NER>
          </token>
          <token id="24">
            <word>excite</word>
            <lemma>excite</lemma>
            <CharacterOffsetBegin>774</CharacterOffsetBegin>
            <CharacterOffsetEnd>780</CharacterOffsetEnd>
            <POS>VB</POS>
            <NER>O</NER>
          </token>
          <token id="25">
            <word>them</word>
            <lemma>they</lemma>
            <CharacterOffsetBegin>781</CharacterOffsetBegin>
            <CharacterOffsetEnd>785</CharacterOffsetEnd>
            <POS>PRP</POS>
            <NER>O</NER>
          </token>
          <token id="26">
            <word>.</word>
            <lemma>.</lemma>
            <CharacterOffsetBegin>785</CharacterOffsetBegin>
            <CharacterOffsetEnd>786</CharacterOffsetEnd>
            <POS>.</POS>
            <NER>O</NER>
          </token>
        </tokens>
      </sentence>
      <sentence id="5">
        <tokens>
          <token id="1">
            <word>However</word>
            <lemma>however</lemma>
            <CharacterOffsetBegin>787</CharacterOffsetBegin>
            <CharacterOffsetEnd>794</CharacterOffsetEnd>
            <POS>RB</POS>
            <NER>O</NER>
          </token>
          <token id="2">
            <word>,</word>
            <lemma>,</lemma>
            <CharacterOffsetBegin>794</CharacterOffsetBegin>
            <CharacterOffsetEnd>795</CharacterOffsetEnd>
            <POS>,</POS>
            <NER>O</NER>
          </token>
          <token id="3">
            <word>Basov</word>
            <lemma>Basov</lemma>
            <CharacterOffsetBegin>796</CharacterOffsetBegin>
            <CharacterOffsetEnd>801</CharacterOffsetEnd>
            <POS>NNP</POS>
            <NER>PERSON</NER>
          </token>
          <token id="4">
            <word>and</word>
            <lemma>and</lemma>
            <CharacterOffsetBegin>802</CharacterOffsetBegin>
            <CharacterOffsetEnd>805</CharacterOffsetEnd>
            <POS>CC</POS>
            <NER>O</NER>
          </token>
          <token id="5">
            <word>his</word>
            <lemma>he</lemma>
            <CharacterOffsetBegin>806</CharacterOffsetBegin>
            <CharacterOffsetEnd>809</CharacterOffsetEnd>
            <POS>PRP$</POS>
            <NER>O</NER>
          </token>
          <token id="6">
            <word>team</word>
            <lemma>team</lemma>
            <CharacterOffsetBegin>810</CharacterOffsetBegin>
            <CharacterOffsetEnd>814</CharacterOffsetEnd>
            <POS>NN</POS>
            <NER>O</NER>
          </token>
          <token id="7">
            <word>of</word>
            <lemma>of</lemma>
            <CharacterOffsetBegin>815</CharacterOffsetBegin>
            <CharacterOffsetEnd>817</CharacterOffsetEnd>
            <POS>IN</POS>
            <NER>O</NER>
          </token>
          <token id="8">
            <word>researchers</word>
            <lemma>researcher</lemma>
            <CharacterOffsetBegin>818</CharacterOffsetBegin>
            <CharacterOffsetEnd>829</CharacterOffsetEnd>
            <POS>NNS</POS>
            <NER>O</NER>
          </token>
          <token id="9">
            <word>have</word>
            <lemma>have</lemma>
            <CharacterOffsetBegin>830</CharacterOffsetBegin>
            <CharacterOffsetEnd>834</CharacterOffsetEnd>
            <POS>VBP</POS>
            <NER>O</NER>
          </token>
          <token id="10">
            <word>discovered</word>
            <lemma>discover</lemma>
            <CharacterOffsetBegin>835</CharacterOffsetBegin>
            <CharacterOffsetEnd>845</CharacterOffsetEnd>
            <POS>VBN</POS>
            <NER>O</NER>
          </token>
          <token id="11">
            <word>that</word>
            <lemma>that</lemma>
            <CharacterOffsetBegin>846</CharacterOffsetBegin>
            <CharacterOffsetEnd>850</CharacterOffsetEnd>
            <POS>IN</POS>
            <NER>O</NER>
          </token>
          <token id="12">
            <word>a</word>
            <lemma>a</lemma>
            <CharacterOffsetBegin>851</CharacterOffsetBegin>
            <CharacterOffsetEnd>852</CharacterOffsetEnd>
            <POS>DT</POS>
            <NER>O</NER>
          </token>
          <token id="13">
            <word>tiny</word>
            <lemma>tiny</lemma>
            <CharacterOffsetBegin>853</CharacterOffsetBegin>
            <CharacterOffsetEnd>857</CharacterOffsetEnd>
            <POS>JJ</POS>
            <NER>O</NER>
          </token>
          <token id="14">
            <word>mental</word>
            <lemma>mental</lemma>
            <CharacterOffsetBegin>858</CharacterOffsetBegin>
            <CharacterOffsetEnd>864</CharacterOffsetEnd>
            <POS>JJ</POS>
            <NER>O</NER>
          </token>
          <token id="15">
            <word>pin</word>
            <lemma>pin</lemma>
            <CharacterOffsetBegin>865</CharacterOffsetBegin>
            <CharacterOffsetEnd>868</CharacterOffsetEnd>
            <POS>NN</POS>
            <NER>O</NER>
          </token>
          <token id="16">
            <word>--</word>
            <lemma>--</lemma>
            <CharacterOffsetBegin>869</CharacterOffsetBegin>
            <CharacterOffsetEnd>870</CharacterOffsetEnd>
            <POS>:</POS>
            <NER>O</NER>
          </token>
          <token id="17">
            <word>whose</word>
            <lemma>whose</lemma>
            <CharacterOffsetBegin>871</CharacterOffsetBegin>
            <CharacterOffsetEnd>876</CharacterOffsetEnd>
            <POS>WP$</POS>
            <NER>O</NER>
          </token>
          <token id="18">
            <word>tip</word>
            <lemma>tip</lemma>
            <CharacterOffsetBegin>877</CharacterOffsetBegin>
            <CharacterOffsetEnd>880</CharacterOffsetEnd>
            <POS>NN</POS>
            <NER>O</NER>
          </token>
          <token id="19">
            <word>measures</word>
            <lemma>measure</lemma>
            <CharacterOffsetBegin>881</CharacterOffsetBegin>
            <CharacterOffsetEnd>889</CharacterOffsetEnd>
            <POS>NNS</POS>
            <NER>O</NER>
          </token>
          <token id="20">
            <word>mere</word>
            <lemma>mere</lemma>
            <CharacterOffsetBegin>890</CharacterOffsetBegin>
            <CharacterOffsetEnd>894</CharacterOffsetEnd>
            <POS>JJ</POS>
            <NER>O</NER>
          </token>
          <token id="21">
            <word>nanometres</word>
            <lemma>nanometre</lemma>
            <CharacterOffsetBegin>895</CharacterOffsetBegin>
            <CharacterOffsetEnd>905</CharacterOffsetEnd>
            <POS>NNS</POS>
            <NER>O</NER>
          </token>
          <token id="22">
            <word>--</word>
            <lemma>--</lemma>
            <CharacterOffsetBegin>906</CharacterOffsetBegin>
            <CharacterOffsetEnd>907</CharacterOffsetEnd>
            <POS>:</POS>
            <NER>O</NER>
          </token>
          <token id="23">
            <word>can</word>
            <lemma>can</lemma>
            <CharacterOffsetBegin>908</CharacterOffsetBegin>
            <CharacterOffsetEnd>911</CharacterOffsetEnd>
            <POS>MD</POS>
            <NER>O</NER>
          </token>
          <token id="24">
            <word>act</word>
            <lemma>act</lemma>
            <CharacterOffsetBegin>912</CharacterOffsetBegin>
            <CharacterOffsetEnd>915</CharacterOffsetEnd>
            <POS>VB</POS>
            <NER>O</NER>
          </token>
          <token id="25">
            <word>a</word>
            <lemma>a</lemma>
            <CharacterOffsetBegin>916</CharacterOffsetBegin>
            <CharacterOffsetEnd>917</CharacterOffsetEnd>
            <POS>DT</POS>
            <NER>O</NER>
          </token>
          <token id="26">
            <word>bit</word>
            <lemma>bit</lemma>
            <CharacterOffsetBegin>918</CharacterOffsetBegin>
            <CharacterOffsetEnd>921</CharacterOffsetEnd>
            <POS>NN</POS>
            <NER>O</NER>
          </token>
          <token id="27">
            <word>like</word>
            <lemma>like</lemma>
            <CharacterOffsetBegin>922</CharacterOffsetBegin>
            <CharacterOffsetEnd>926</CharacterOffsetEnd>
            <POS>IN</POS>
            <NER>O</NER>
          </token>
          <token id="28">
            <word>a</word>
            <lemma>a</lemma>
            <CharacterOffsetBegin>927</CharacterOffsetBegin>
            <CharacterOffsetEnd>928</CharacterOffsetEnd>
            <POS>DT</POS>
            <NER>O</NER>
          </token>
          <token id="29">
            <word>lightning</word>
            <lemma>lightning</lemma>
            <CharacterOffsetBegin>929</CharacterOffsetBegin>
            <CharacterOffsetEnd>938</CharacterOffsetEnd>
            <POS>NN</POS>
            <NER>O</NER>
          </token>
          <token id="30">
            <word>rod</word>
            <lemma>rod</lemma>
            <CharacterOffsetBegin>939</CharacterOffsetBegin>
            <CharacterOffsetEnd>942</CharacterOffsetEnd>
            <POS>NN</POS>
            <NER>O</NER>
          </token>
          <token id="31">
            <word>,</word>
            <lemma>,</lemma>
            <CharacterOffsetBegin>942</CharacterOffsetBegin>
            <CharacterOffsetEnd>943</CharacterOffsetEnd>
            <POS>,</POS>
            <NER>O</NER>
          </token>
          <token id="32">
            <word>focussing</word>
            <lemma>focus</lemma>
            <CharacterOffsetBegin>944</CharacterOffsetBegin>
            <CharacterOffsetEnd>953</CharacterOffsetEnd>
            <POS>VBG</POS>
            <NER>O</NER>
          </token>
          <token id="33">
            <word>all</word>
            <lemma>all</lemma>
            <CharacterOffsetBegin>954</CharacterOffsetBegin>
            <CharacterOffsetEnd>957</CharacterOffsetEnd>
            <POS>PDT</POS>
            <NER>O</NER>
          </token>
          <token id="34">
            <word>the</word>
            <lemma>the</lemma>
            <CharacterOffsetBegin>958</CharacterOffsetBegin>
            <CharacterOffsetEnd>961</CharacterOffsetEnd>
            <POS>DT</POS>
            <NER>O</NER>
          </token>
          <token id="35">
            <word>incident</word>
            <lemma>incident</lemma>
            <CharacterOffsetBegin>962</CharacterOffsetBegin>
            <CharacterOffsetEnd>970</CharacterOffsetEnd>
            <POS>NN</POS>
            <NER>O</NER>
          </token>
          <token id="36">
            <word>photons</word>
            <lemma>photon</lemma>
            <CharacterOffsetBegin>971</CharacterOffsetBegin>
            <CharacterOffsetEnd>978</CharacterOffsetEnd>
            <POS>NNS</POS>
            <NER>O</NER>
          </token>
          <token id="37">
            <word>in</word>
            <lemma>in</lemma>
            <CharacterOffsetBegin>979</CharacterOffsetBegin>
            <CharacterOffsetEnd>981</CharacterOffsetEnd>
            <POS>IN</POS>
            <NER>O</NER>
          </token>
          <token id="38">
            <word>a</word>
            <lemma>a</lemma>
            <CharacterOffsetBegin>982</CharacterOffsetBegin>
            <CharacterOffsetEnd>983</CharacterOffsetEnd>
            <POS>DT</POS>
            <NER>O</NER>
          </token>
          <token id="39">
            <word>small</word>
            <lemma>small</lemma>
            <CharacterOffsetBegin>984</CharacterOffsetBegin>
            <CharacterOffsetEnd>989</CharacterOffsetEnd>
            <POS>JJ</POS>
            <NER>O</NER>
          </token>
          <token id="40">
            <word>region</word>
            <lemma>region</lemma>
            <CharacterOffsetBegin>990</CharacterOffsetBegin>
            <CharacterOffsetEnd>996</CharacterOffsetEnd>
            <POS>NN</POS>
            <NER>O</NER>
          </token>
          <token id="41">
            <word>.</word>
            <lemma>.</lemma>
            <CharacterOffsetBegin>996</CharacterOffsetBegin>
            <CharacterOffsetEnd>997</CharacterOffsetEnd>
            <POS>.</POS>
            <NER>O</NER>
          </token>
        </tokens>
      </sentence>
      <sentence id="6">
        <tokens>
          <token id="1">
            <word>This</word>
            <lemma>this</lemma>
            <CharacterOffsetBegin>998</CharacterOffsetBegin>
            <CharacterOffsetEnd>1002</CharacterOffsetEnd>
            <POS>DT</POS>
            <NER>O</NER>
          </token>
          <token id="2">
            <word>raises</word>
            <lemma>raise</lemma>
            <CharacterOffsetBegin>1003</CharacterOffsetBegin>
            <CharacterOffsetEnd>1009</CharacterOffsetEnd>
            <POS>VBZ</POS>
            <NER>O</NER>
          </token>
          <token id="3">
            <word>the</word>
            <lemma>the</lemma>
            <CharacterOffsetBegin>1010</CharacterOffsetBegin>
            <CharacterOffsetEnd>1013</CharacterOffsetEnd>
            <POS>DT</POS>
            <NER>O</NER>
          </token>
          <token id="4">
            <word>momentum</word>
            <lemma>momentum</lemma>
            <CharacterOffsetBegin>1014</CharacterOffsetBegin>
            <CharacterOffsetEnd>1022</CharacterOffsetEnd>
            <POS>NN</POS>
            <NER>O</NER>
          </token>
          <token id="5">
            <word>of</word>
            <lemma>of</lemma>
            <CharacterOffsetBegin>1023</CharacterOffsetBegin>
            <CharacterOffsetEnd>1025</CharacterOffsetEnd>
            <POS>IN</POS>
            <NER>O</NER>
          </token>
          <token id="6">
            <word>the</word>
            <lemma>the</lemma>
            <CharacterOffsetBegin>1026</CharacterOffsetBegin>
            <CharacterOffsetEnd>1029</CharacterOffsetEnd>
            <POS>DT</POS>
            <NER>O</NER>
          </token>
          <token id="7">
            <word>IR</word>
            <lemma>IR</lemma>
            <CharacterOffsetBegin>1030</CharacterOffsetBegin>
            <CharacterOffsetEnd>1032</CharacterOffsetEnd>
            <POS>NNP</POS>
            <NER>O</NER>
          </token>
          <token id="8">
            <word>photons</word>
            <lemma>photon</lemma>
            <CharacterOffsetBegin>1033</CharacterOffsetBegin>
            <CharacterOffsetEnd>1040</CharacterOffsetEnd>
            <POS>NNS</POS>
            <NER>O</NER>
          </token>
          <token id="9">
            <word>significantly</word>
            <lemma>significantly</lemma>
            <CharacterOffsetBegin>1041</CharacterOffsetBegin>
            <CharacterOffsetEnd>1054</CharacterOffsetEnd>
            <POS>RB</POS>
            <NER>O</NER>
          </token>
          <token id="10">
            <word>--</word>
            <lemma>--</lemma>
            <CharacterOffsetBegin>1055</CharacterOffsetBegin>
            <CharacterOffsetEnd>1056</CharacterOffsetEnd>
            <POS>:</POS>
            <NER>O</NER>
          </token>
          <token id="11">
            <word>60</word>
            <lemma>60</lemma>
            <CharacterOffsetBegin>1057</CharacterOffsetBegin>
            <CharacterOffsetEnd>1059</CharacterOffsetEnd>
            <POS>CD</POS>
            <NER>NUMBER</NER>
            <NormalizedNER>60.0</NormalizedNER>
          </token>
          <token id="12">
            <word>time</word>
            <lemma>time</lemma>
            <CharacterOffsetBegin>1060</CharacterOffsetBegin>
            <CharacterOffsetEnd>1064</CharacterOffsetEnd>
            <POS>NN</POS>
            <NER>O</NER>
          </token>
          <token id="13">
            <word>,</word>
            <lemma>,</lemma>
            <CharacterOffsetBegin>1064</CharacterOffsetBegin>
            <CharacterOffsetEnd>1065</CharacterOffsetEnd>
            <POS>,</POS>
            <NER>O</NER>
          </token>
          <token id="14">
            <word>per</word>
            <lemma>per</lemma>
            <CharacterOffsetBegin>1066</CharacterOffsetBegin>
            <CharacterOffsetEnd>1069</CharacterOffsetEnd>
            <POS>IN</POS>
            <NER>O</NER>
          </token>
          <token id="15">
            <word>the</word>
            <lemma>the</lemma>
            <CharacterOffsetBegin>1070</CharacterOffsetBegin>
            <CharacterOffsetEnd>1073</CharacterOffsetEnd>
            <POS>DT</POS>
            <NER>O</NER>
          </token>
          <token id="16">
            <word>press</word>
            <lemma>press</lemma>
            <CharacterOffsetBegin>1074</CharacterOffsetBegin>
            <CharacterOffsetEnd>1079</CharacterOffsetEnd>
            <POS>NN</POS>
            <NER>O</NER>
          </token>
          <token id="17">
            <word>release</word>
            <lemma>release</lemma>
            <CharacterOffsetBegin>1080</CharacterOffsetBegin>
            <CharacterOffsetEnd>1087</CharacterOffsetEnd>
            <POS>NN</POS>
            <NER>O</NER>
          </token>
          <token id="18">
            <word>here</word>
            <lemma>here</lemma>
            <CharacterOffsetBegin>1088</CharacterOffsetBegin>
            <CharacterOffsetEnd>1092</CharacterOffsetEnd>
            <POS>RB</POS>
            <NER>O</NER>
          </token>
          <token id="19">
            <word>-</word>
            <lemma>-</lemma>
            <CharacterOffsetBegin>1093</CharacterOffsetBegin>
            <CharacterOffsetEnd>1094</CharacterOffsetEnd>
            <POS>:</POS>
            <NER>O</NER>
          </token>
          <token id="20">
            <word>which</word>
            <lemma>which</lemma>
            <CharacterOffsetBegin>1095</CharacterOffsetBegin>
            <CharacterOffsetEnd>1100</CharacterOffsetEnd>
            <POS>WDT</POS>
            <NER>O</NER>
          </token>
          <token id="21">
            <word>is</word>
            <lemma>be</lemma>
            <CharacterOffsetBegin>1101</CharacterOffsetBegin>
            <CharacterOffsetEnd>1103</CharacterOffsetEnd>
            <POS>VBZ</POS>
            <NER>O</NER>
          </token>
          <token id="22">
            <word>enough</word>
            <lemma>enough</lemma>
            <CharacterOffsetBegin>1104</CharacterOffsetBegin>
            <CharacterOffsetEnd>1110</CharacterOffsetEnd>
            <POS>JJ</POS>
            <NER>O</NER>
          </token>
          <token id="23">
            <word>to</word>
            <lemma>to</lemma>
            <CharacterOffsetBegin>1111</CharacterOffsetBegin>
            <CharacterOffsetEnd>1113</CharacterOffsetEnd>
            <POS>TO</POS>
            <NER>O</NER>
          </token>
          <token id="24">
            <word>``</word>
            <lemma>``</lemma>
            <CharacterOffsetBegin>1114</CharacterOffsetBegin>
            <CharacterOffsetEnd>1115</CharacterOffsetEnd>
            <POS>``</POS>
            <NER>O</NER>
          </token>
          <token id="25">
            <word>launch</word>
            <lemma>launch</lemma>
            <CharacterOffsetBegin>1115</CharacterOffsetBegin>
            <CharacterOffsetEnd>1121</CharacterOffsetEnd>
            <POS>VB</POS>
            <NER>O</NER>
          </token>
          <token id="26">
            <word>plasmonic</word>
            <lemma>plasmonic</lemma>
            <CharacterOffsetBegin>1122</CharacterOffsetBegin>
            <CharacterOffsetEnd>1131</CharacterOffsetEnd>
            <POS>JJ</POS>
            <NER>O</NER>
          </token>
          <token id="27">
            <word>waves</word>
            <lemma>wave</lemma>
            <CharacterOffsetBegin>1132</CharacterOffsetBegin>
            <CharacterOffsetEnd>1137</CharacterOffsetEnd>
            <POS>NNS</POS>
            <NER>O</NER>
          </token>
          <token id="28">
            <word>along</word>
            <lemma>along</lemma>
            <CharacterOffsetBegin>1138</CharacterOffsetBegin>
            <CharacterOffsetEnd>1143</CharacterOffsetEnd>
            <POS>IN</POS>
            <NER>O</NER>
          </token>
          <token id="29">
            <word>the</word>
            <lemma>the</lemma>
            <CharacterOffsetBegin>1144</CharacterOffsetBegin>
            <CharacterOffsetEnd>1147</CharacterOffsetEnd>
            <POS>DT</POS>
            <NER>O</NER>
          </token>
          <token id="30">
            <word>graphene</word>
            <lemma>graphene</lemma>
            <CharacterOffsetBegin>1148</CharacterOffsetBegin>
            <CharacterOffsetEnd>1156</CharacterOffsetEnd>
            <POS>NN</POS>
            <NER>O</NER>
          </token>
          <token id="31">
            <word>layer</word>
            <lemma>layer</lemma>
            <CharacterOffsetBegin>1157</CharacterOffsetBegin>
            <CharacterOffsetEnd>1162</CharacterOffsetEnd>
            <POS>NN</POS>
            <NER>O</NER>
          </token>
          <token id="32">
            <word>''</word>
            <lemma>''</lemma>
            <CharacterOffsetBegin>1162</CharacterOffsetBegin>
            <CharacterOffsetEnd>1163</CharacterOffsetEnd>
            <POS>''</POS>
            <NER>O</NER>
          </token>
          <token id="33">
            <word>.</word>
            <lemma>.</lemma>
            <CharacterOffsetBegin>1163</CharacterOffsetBegin>
            <CharacterOffsetEnd>1164</CharacterOffsetEnd>
            <POS>.</POS>
            <NER>O</NER>
          </token>
        </tokens>
      </sentence>
      <sentence id="7">
        <tokens>
          <token id="1">
            <word>``</word>
            <lemma>``</lemma>
            <CharacterOffsetBegin>1165</CharacterOffsetBegin>
            <CharacterOffsetEnd>1166</CharacterOffsetEnd>
            <POS>``</POS>
            <NER>O</NER>
          </token>
          <token id="2">
            <word>It</word>
            <lemma>it</lemma>
            <CharacterOffsetBegin>1166</CharacterOffsetBegin>
            <CharacterOffsetEnd>1168</CharacterOffsetEnd>
            <POS>PRP</POS>
            <NER>O</NER>
          </token>
          <token id="3">
            <word>is</word>
            <lemma>be</lemma>
            <CharacterOffsetBegin>1169</CharacterOffsetBegin>
            <CharacterOffsetEnd>1171</CharacterOffsetEnd>
            <POS>VBZ</POS>
            <NER>O</NER>
          </token>
          <token id="4">
            <word>even</word>
            <lemma>even</lemma>
            <CharacterOffsetBegin>1172</CharacterOffsetBegin>
            <CharacterOffsetEnd>1176</CharacterOffsetEnd>
            <POS>RB</POS>
            <NER>O</NER>
          </token>
          <token id="5">
            <word>possible</word>
            <lemma>possible</lemma>
            <CharacterOffsetBegin>1177</CharacterOffsetBegin>
            <CharacterOffsetEnd>1185</CharacterOffsetEnd>
            <POS>JJ</POS>
            <NER>O</NER>
          </token>
          <token id="6">
            <word>to</word>
            <lemma>to</lemma>
            <CharacterOffsetBegin>1186</CharacterOffsetBegin>
            <CharacterOffsetEnd>1188</CharacterOffsetEnd>
            <POS>TO</POS>
            <NER>O</NER>
          </token>
          <token id="7">
            <word>control</word>
            <lemma>control</lemma>
            <CharacterOffsetBegin>1189</CharacterOffsetBegin>
            <CharacterOffsetEnd>1196</CharacterOffsetEnd>
            <POS>VB</POS>
            <NER>O</NER>
          </token>
          <token id="8">
            <word>the</word>
            <lemma>the</lemma>
            <CharacterOffsetBegin>1197</CharacterOffsetBegin>
            <CharacterOffsetEnd>1200</CharacterOffsetEnd>
            <POS>DT</POS>
            <NER>O</NER>
          </token>
          <token id="9">
            <word>light</word>
            <lemma>light</lemma>
            <CharacterOffsetBegin>1201</CharacterOffsetBegin>
            <CharacterOffsetEnd>1206</CharacterOffsetEnd>
            <POS>JJ</POS>
            <NER>O</NER>
          </token>
          <token id="10">
            <word>waves</word>
            <lemma>wave</lemma>
            <CharacterOffsetBegin>1207</CharacterOffsetBegin>
            <CharacterOffsetEnd>1212</CharacterOffsetEnd>
            <POS>NNS</POS>
            <NER>O</NER>
          </token>
          <token id="11">
            <word>within</word>
            <lemma>within</lemma>
            <CharacterOffsetBegin>1213</CharacterOffsetBegin>
            <CharacterOffsetEnd>1219</CharacterOffsetEnd>
            <POS>IN</POS>
            <NER>O</NER>
          </token>
          <token id="12">
            <word>the</word>
            <lemma>the</lemma>
            <CharacterOffsetBegin>1220</CharacterOffsetBegin>
            <CharacterOffsetEnd>1223</CharacterOffsetEnd>
            <POS>DT</POS>
            <NER>O</NER>
          </token>
          <token id="13">
            <word>lattice</word>
            <lemma>lattice</lemma>
            <CharacterOffsetBegin>1224</CharacterOffsetBegin>
            <CharacterOffsetEnd>1231</CharacterOffsetEnd>
            <POS>NN</POS>
            <NER>O</NER>
          </token>
          <token id="14">
            <word>,</word>
            <lemma>,</lemma>
            <CharacterOffsetBegin>1231</CharacterOffsetBegin>
            <CharacterOffsetEnd>1232</CharacterOffsetEnd>
            <POS>,</POS>
            <NER>O</NER>
          </token>
          <token id="15">
            <word>''</word>
            <lemma>''</lemma>
            <CharacterOffsetBegin>1232</CharacterOffsetBegin>
            <CharacterOffsetEnd>1233</CharacterOffsetEnd>
            <POS>''</POS>
            <NER>O</NER>
          </token>
          <token id="16">
            <word>says</word>
            <lemma>say</lemma>
            <CharacterOffsetBegin>1234</CharacterOffsetBegin>
            <CharacterOffsetEnd>1238</CharacterOffsetEnd>
            <POS>VBZ</POS>
            <NER>O</NER>
          </token>
          <token id="17">
            <word>Dr.</word>
            <lemma>Dr.</lemma>
            <CharacterOffsetBegin>1239</CharacterOffsetBegin>
            <CharacterOffsetEnd>1242</CharacterOffsetEnd>
            <POS>NNP</POS>
            <NER>O</NER>
          </token>
          <token id="18">
            <word>Fritz</word>
            <lemma>Fritz</lemma>
            <CharacterOffsetBegin>1243</CharacterOffsetBegin>
            <CharacterOffsetEnd>1248</CharacterOffsetEnd>
            <POS>NNP</POS>
            <NER>PERSON</NER>
          </token>
          <token id="19">
            <word>Keilmann</word>
            <lemma>Keilmann</lemma>
            <CharacterOffsetBegin>1249</CharacterOffsetBegin>
            <CharacterOffsetEnd>1257</CharacterOffsetEnd>
            <POS>NNP</POS>
            <NER>PERSON</NER>
          </token>
          <token id="20">
            <word>,</word>
            <lemma>,</lemma>
            <CharacterOffsetBegin>1257</CharacterOffsetBegin>
            <CharacterOffsetEnd>1258</CharacterOffsetEnd>
            <POS>,</POS>
            <NER>O</NER>
          </token>
          <token id="21">
            <word>who</word>
            <lemma>who</lemma>
            <CharacterOffsetBegin>1259</CharacterOffsetBegin>
            <CharacterOffsetEnd>1262</CharacterOffsetEnd>
            <POS>WP</POS>
            <NER>O</NER>
          </token>
          <token id="22">
            <word>works</word>
            <lemma>work</lemma>
            <CharacterOffsetBegin>1263</CharacterOffsetBegin>
            <CharacterOffsetEnd>1268</CharacterOffsetEnd>
            <POS>VBZ</POS>
            <NER>O</NER>
          </token>
          <token id="23">
            <word>at</word>
            <lemma>at</lemma>
            <CharacterOffsetBegin>1269</CharacterOffsetBegin>
            <CharacterOffsetEnd>1271</CharacterOffsetEnd>
            <POS>IN</POS>
            <NER>O</NER>
          </token>
          <token id="24">
            <word>the</word>
            <lemma>the</lemma>
            <CharacterOffsetBegin>1272</CharacterOffsetBegin>
            <CharacterOffsetEnd>1275</CharacterOffsetEnd>
            <POS>DT</POS>
            <NER>O</NER>
          </token>
          <token id="25">
            <word>Ludwig-Maximilians-Universitaet</word>
            <lemma>Ludwig-Maximilians-Universitaet</lemma>
            <CharacterOffsetBegin>1276</CharacterOffsetBegin>
            <CharacterOffsetEnd>1307</CharacterOffsetEnd>
            <POS>NNP</POS>
            <NER>O</NER>
          </token>
          <token id="26">
            <word>,</word>
            <lemma>,</lemma>
            <CharacterOffsetBegin>1307</CharacterOffsetBegin>
            <CharacterOffsetEnd>1308</CharacterOffsetEnd>
            <POS>,</POS>
            <NER>O</NER>
          </token>
          <token id="27">
            <word>the</word>
            <lemma>the</lemma>
            <CharacterOffsetBegin>1309</CharacterOffsetBegin>
            <CharacterOffsetEnd>1312</CharacterOffsetEnd>
            <POS>DT</POS>
            <NER>O</NER>
          </token>
          <token id="28">
            <word>Center</word>
            <lemma>Center</lemma>
            <CharacterOffsetBegin>1313</CharacterOffsetBegin>
            <CharacterOffsetEnd>1319</CharacterOffsetEnd>
            <POS>NNP</POS>
            <NER>O</NER>
          </token>
          <token id="29">
            <word>for</word>
            <lemma>for</lemma>
            <CharacterOffsetBegin>1320</CharacterOffsetBegin>
            <CharacterOffsetEnd>1323</CharacterOffsetEnd>
            <POS>IN</POS>
            <NER>O</NER>
          </token>
          <token id="30">
            <word>Nanoscience</word>
            <lemma>Nanoscience</lemma>
            <CharacterOffsetBegin>1324</CharacterOffsetBegin>
            <CharacterOffsetEnd>1335</CharacterOffsetEnd>
            <POS>NNP</POS>
            <NER>O</NER>
          </token>
          <token id="31">
            <word>,</word>
            <lemma>,</lemma>
            <CharacterOffsetBegin>1335</CharacterOffsetBegin>
            <CharacterOffsetEnd>1336</CharacterOffsetEnd>
            <POS>,</POS>
            <NER>O</NER>
          </token>
          <token id="32">
            <word>and</word>
            <lemma>and</lemma>
            <CharacterOffsetBegin>1337</CharacterOffsetBegin>
            <CharacterOffsetEnd>1340</CharacterOffsetEnd>
            <POS>CC</POS>
            <NER>O</NER>
          </token>
          <token id="33">
            <word>the</word>
            <lemma>the</lemma>
            <CharacterOffsetBegin>1341</CharacterOffsetBegin>
            <CharacterOffsetEnd>1344</CharacterOffsetEnd>
            <POS>DT</POS>
            <NER>O</NER>
          </token>
          <token id="34">
            <word>Max</word>
            <lemma>Max</lemma>
            <CharacterOffsetBegin>1345</CharacterOffsetBegin>
            <CharacterOffsetEnd>1348</CharacterOffsetEnd>
            <POS>NNP</POS>
            <NER>ORGANIZATION</NER>
          </token>
          <token id="35">
            <word>Planck</word>
            <lemma>Planck</lemma>
            <CharacterOffsetBegin>1349</CharacterOffsetBegin>
            <CharacterOffsetEnd>1355</CharacterOffsetEnd>
            <POS>NNP</POS>
            <NER>ORGANIZATION</NER>
          </token>
          <token id="36">
            <word>Institute</word>
            <lemma>Institute</lemma>
            <CharacterOffsetBegin>1356</CharacterOffsetBegin>
            <CharacterOffsetEnd>1365</CharacterOffsetEnd>
            <POS>NNP</POS>
            <NER>ORGANIZATION</NER>
          </token>
          <token id="37">
            <word>for</word>
            <lemma>for</lemma>
            <CharacterOffsetBegin>1366</CharacterOffsetBegin>
            <CharacterOffsetEnd>1369</CharacterOffsetEnd>
            <POS>IN</POS>
            <NER>ORGANIZATION</NER>
          </token>
          <token id="38">
            <word>Quantum</word>
            <lemma>Quantum</lemma>
            <CharacterOffsetBegin>1370</CharacterOffsetBegin>
            <CharacterOffsetEnd>1377</CharacterOffsetEnd>
            <POS>NNP</POS>
            <NER>ORGANIZATION</NER>
          </token>
          <token id="39">
            <word>Optics</word>
            <lemma>Optics</lemma>
            <CharacterOffsetBegin>1378</CharacterOffsetBegin>
            <CharacterOffsetEnd>1384</CharacterOffsetEnd>
            <POS>NNP</POS>
            <NER>ORGANIZATION</NER>
          </token>
          <token id="40">
            <word>.</word>
            <lemma>.</lemma>
            <CharacterOffsetBegin>1384</CharacterOffsetBegin>
            <CharacterOffsetEnd>1385</CharacterOffsetEnd>
            <POS>.</POS>
            <NER>O</NER>
          </token>
        </tokens>
      </sentence>
      <sentence id="8">
        <tokens>
          <token id="1">
            <word>``</word>
            <lemma>``</lemma>
            <CharacterOffsetBegin>1386</CharacterOffsetBegin>
            <CharacterOffsetEnd>1387</CharacterOffsetEnd>
            <POS>``</POS>
            <NER>O</NER>
          </token>
          <token id="2">
            <word>It</word>
            <lemma>it</lemma>
            <CharacterOffsetBegin>1387</CharacterOffsetBegin>
            <CharacterOffsetEnd>1389</CharacterOffsetEnd>
            <POS>PRP</POS>
            <NER>O</NER>
          </token>
          <token id="3">
            <word>might</word>
            <lemma>might</lemma>
            <CharacterOffsetBegin>1390</CharacterOffsetBegin>
            <CharacterOffsetEnd>1395</CharacterOffsetEnd>
            <POS>MD</POS>
            <NER>O</NER>
          </token>
          <token id="4">
            <word>even</word>
            <lemma>even</lemma>
            <CharacterOffsetBegin>1396</CharacterOffsetBegin>
            <CharacterOffsetEnd>1400</CharacterOffsetEnd>
            <POS>RB</POS>
            <NER>O</NER>
          </token>
          <token id="5">
            <word>be</word>
            <lemma>be</lemma>
            <CharacterOffsetBegin>1401</CharacterOffsetBegin>
            <CharacterOffsetEnd>1403</CharacterOffsetEnd>
            <POS>VB</POS>
            <NER>O</NER>
          </token>
          <token id="6">
            <word>possible</word>
            <lemma>possible</lemma>
            <CharacterOffsetBegin>1404</CharacterOffsetBegin>
            <CharacterOffsetEnd>1412</CharacterOffsetEnd>
            <POS>JJ</POS>
            <NER>O</NER>
          </token>
          <token id="7">
            <word>to</word>
            <lemma>to</lemma>
            <CharacterOffsetBegin>1413</CharacterOffsetBegin>
            <CharacterOffsetEnd>1415</CharacterOffsetEnd>
            <POS>TO</POS>
            <NER>O</NER>
          </token>
          <token id="8">
            <word>develop</word>
            <lemma>develop</lemma>
            <CharacterOffsetBegin>1416</CharacterOffsetBegin>
            <CharacterOffsetEnd>1423</CharacterOffsetEnd>
            <POS>VB</POS>
            <NER>O</NER>
          </token>
          <token id="9">
            <word>computers</word>
            <lemma>computer</lemma>
            <CharacterOffsetBegin>1424</CharacterOffsetBegin>
            <CharacterOffsetEnd>1433</CharacterOffsetEnd>
            <POS>NNS</POS>
            <NER>O</NER>
          </token>
          <token id="10">
            <word>whose</word>
            <lemma>whose</lemma>
            <CharacterOffsetBegin>1434</CharacterOffsetBegin>
            <CharacterOffsetEnd>1439</CharacterOffsetEnd>
            <POS>WP$</POS>
            <NER>O</NER>
          </token>
          <token id="11">
            <word>graphene</word>
            <lemma>graphene</lemma>
            <CharacterOffsetBegin>1440</CharacterOffsetBegin>
            <CharacterOffsetEnd>1448</CharacterOffsetEnd>
            <POS>NN</POS>
            <NER>O</NER>
          </token>
          <token id="12">
            <word>transistors</word>
            <lemma>transistor</lemma>
            <CharacterOffsetBegin>1449</CharacterOffsetBegin>
            <CharacterOffsetEnd>1460</CharacterOffsetEnd>
            <POS>NNS</POS>
            <NER>O</NER>
          </token>
          <token id="13">
            <word>could</word>
            <lemma>could</lemma>
            <CharacterOffsetBegin>1461</CharacterOffsetBegin>
            <CharacterOffsetEnd>1466</CharacterOffsetEnd>
            <POS>MD</POS>
            <NER>O</NER>
          </token>
          <token id="14">
            <word>be</word>
            <lemma>be</lemma>
            <CharacterOffsetBegin>1467</CharacterOffsetBegin>
            <CharacterOffsetEnd>1469</CharacterOffsetEnd>
            <POS>VB</POS>
            <NER>O</NER>
          </token>
          <token id="15">
            <word>switched</word>
            <lemma>switch</lemma>
            <CharacterOffsetBegin>1470</CharacterOffsetBegin>
            <CharacterOffsetEnd>1478</CharacterOffsetEnd>
            <POS>VBN</POS>
            <NER>O</NER>
          </token>
          <token id="16">
            <word>both</word>
            <lemma>both</lemma>
            <CharacterOffsetBegin>1479</CharacterOffsetBegin>
            <CharacterOffsetEnd>1483</CharacterOffsetEnd>
            <POS>DT</POS>
            <NER>O</NER>
          </token>
          <token id="17">
            <word>optically</word>
            <lemma>optically</lemma>
            <CharacterOffsetBegin>1484</CharacterOffsetBegin>
            <CharacterOffsetEnd>1493</CharacterOffsetEnd>
            <POS>RB</POS>
            <NER>O</NER>
          </token>
          <token id="18">
            <word>and</word>
            <lemma>and</lemma>
            <CharacterOffsetBegin>1494</CharacterOffsetBegin>
            <CharacterOffsetEnd>1497</CharacterOffsetEnd>
            <POS>CC</POS>
            <NER>O</NER>
          </token>
          <token id="19">
            <word>electrically</word>
            <lemma>electrically</lemma>
            <CharacterOffsetBegin>1498</CharacterOffsetBegin>
            <CharacterOffsetEnd>1510</CharacterOffsetEnd>
            <POS>RB</POS>
            <NER>O</NER>
          </token>
          <token id="20">
            <word>,</word>
            <lemma>,</lemma>
            <CharacterOffsetBegin>1510</CharacterOffsetBegin>
            <CharacterOffsetEnd>1511</CharacterOffsetEnd>
            <POS>,</POS>
            <NER>O</NER>
          </token>
          <token id="21">
            <word>''</word>
            <lemma>''</lemma>
            <CharacterOffsetBegin>1511</CharacterOffsetBegin>
            <CharacterOffsetEnd>1512</CharacterOffsetEnd>
            <POS>''</POS>
            <NER>O</NER>
          </token>
          <token id="22">
            <word>he</word>
            <lemma>he</lemma>
            <CharacterOffsetBegin>1513</CharacterOffsetBegin>
            <CharacterOffsetEnd>1515</CharacterOffsetEnd>
            <POS>PRP</POS>
            <NER>O</NER>
          </token>
          <token id="23">
            <word>added</word>
            <lemma>add</lemma>
            <CharacterOffsetBegin>1516</CharacterOffsetBegin>
            <CharacterOffsetEnd>1521</CharacterOffsetEnd>
            <POS>VBD</POS>
            <NER>O</NER>
          </token>
          <token id="24">
            <word>.</word>
            <lemma>.</lemma>
            <CharacterOffsetBegin>1521</CharacterOffsetBegin>
            <CharacterOffsetEnd>1522</CharacterOffsetEnd>
            <POS>.</POS>
            <NER>O</NER>
          </token>
        </tokens>
      </sentence>
      <sentence id="9">
        <tokens>
          <token id="1">
            <word>This</word>
            <lemma>this</lemma>
            <CharacterOffsetBegin>1523</CharacterOffsetBegin>
            <CharacterOffsetEnd>1527</CharacterOffsetEnd>
            <POS>DT</POS>
            <NER>O</NER>
          </token>
          <token id="2">
            <word>is</word>
            <lemma>be</lemma>
            <CharacterOffsetBegin>1528</CharacterOffsetBegin>
            <CharacterOffsetEnd>1530</CharacterOffsetEnd>
            <POS>VBZ</POS>
            <NER>O</NER>
          </token>
          <token id="3">
            <word>because</word>
            <lemma>because</lemma>
            <CharacterOffsetBegin>1531</CharacterOffsetBegin>
            <CharacterOffsetEnd>1538</CharacterOffsetEnd>
            <POS>IN</POS>
            <NER>O</NER>
          </token>
          <token id="4">
            <word>the</word>
            <lemma>the</lemma>
            <CharacterOffsetBegin>1539</CharacterOffsetBegin>
            <CharacterOffsetEnd>1542</CharacterOffsetEnd>
            <POS>DT</POS>
            <NER>O</NER>
          </token>
          <token id="5">
            <word>light</word>
            <lemma>light</lemma>
            <CharacterOffsetBegin>1543</CharacterOffsetBegin>
            <CharacterOffsetEnd>1548</CharacterOffsetEnd>
            <POS>JJ</POS>
            <NER>O</NER>
          </token>
          <token id="6">
            <word>waves</word>
            <lemma>wave</lemma>
            <CharacterOffsetBegin>1549</CharacterOffsetBegin>
            <CharacterOffsetEnd>1554</CharacterOffsetEnd>
            <POS>NNS</POS>
            <NER>O</NER>
          </token>
          <token id="7">
            <word>in</word>
            <lemma>in</lemma>
            <CharacterOffsetBegin>1555</CharacterOffsetBegin>
            <CharacterOffsetEnd>1557</CharacterOffsetEnd>
            <POS>IN</POS>
            <NER>O</NER>
          </token>
          <token id="8">
            <word>the</word>
            <lemma>the</lemma>
            <CharacterOffsetBegin>1558</CharacterOffsetBegin>
            <CharacterOffsetEnd>1561</CharacterOffsetEnd>
            <POS>DT</POS>
            <NER>O</NER>
          </token>
          <token id="9">
            <word>graphene</word>
            <lemma>graphene</lemma>
            <CharacterOffsetBegin>1562</CharacterOffsetBegin>
            <CharacterOffsetEnd>1570</CharacterOffsetEnd>
            <POS>NN</POS>
            <NER>O</NER>
          </token>
          <token id="10">
            <word>can</word>
            <lemma>can</lemma>
            <CharacterOffsetBegin>1571</CharacterOffsetBegin>
            <CharacterOffsetEnd>1574</CharacterOffsetEnd>
            <POS>MD</POS>
            <NER>O</NER>
          </token>
          <token id="11">
            <word>be</word>
            <lemma>be</lemma>
            <CharacterOffsetBegin>1575</CharacterOffsetBegin>
            <CharacterOffsetEnd>1577</CharacterOffsetEnd>
            <POS>VB</POS>
            <NER>O</NER>
          </token>
          <token id="12">
            <word>controlled</word>
            <lemma>control</lemma>
            <CharacterOffsetBegin>1578</CharacterOffsetBegin>
            <CharacterOffsetEnd>1588</CharacterOffsetEnd>
            <POS>VBN</POS>
            <NER>O</NER>
          </token>
          <token id="13">
            <word>by</word>
            <lemma>by</lemma>
            <CharacterOffsetBegin>1589</CharacterOffsetBegin>
            <CharacterOffsetEnd>1591</CharacterOffsetEnd>
            <POS>IN</POS>
            <NER>O</NER>
          </token>
          <token id="14">
            <word>electric</word>
            <lemma>electric</lemma>
            <CharacterOffsetBegin>1592</CharacterOffsetBegin>
            <CharacterOffsetEnd>1600</CharacterOffsetEnd>
            <POS>JJ</POS>
            <NER>O</NER>
          </token>
          <token id="15">
            <word>fields</word>
            <lemma>field</lemma>
            <CharacterOffsetBegin>1601</CharacterOffsetBegin>
            <CharacterOffsetEnd>1607</CharacterOffsetEnd>
            <POS>NNS</POS>
            <NER>O</NER>
          </token>
          <token id="16">
            <word>and</word>
            <lemma>and</lemma>
            <CharacterOffsetBegin>1608</CharacterOffsetBegin>
            <CharacterOffsetEnd>1611</CharacterOffsetEnd>
            <POS>CC</POS>
            <NER>O</NER>
          </token>
          <token id="17">
            <word>currents</word>
            <lemma>current</lemma>
            <CharacterOffsetBegin>1612</CharacterOffsetBegin>
            <CharacterOffsetEnd>1620</CharacterOffsetEnd>
            <POS>NNS</POS>
            <NER>O</NER>
          </token>
          <token id="18">
            <word>.</word>
            <lemma>.</lemma>
            <CharacterOffsetBegin>1620</CharacterOffsetBegin>
            <CharacterOffsetEnd>1621</CharacterOffsetEnd>
            <POS>.</POS>
            <NER>O</NER>
          </token>
        </tokens>
      </sentence>
      <sentence id="10">
        <tokens>
          <token id="1">
            <word>This</word>
            <lemma>this</lemma>
            <CharacterOffsetBegin>1622</CharacterOffsetBegin>
            <CharacterOffsetEnd>1626</CharacterOffsetEnd>
            <POS>DT</POS>
            <NER>O</NER>
          </token>
          <token id="2">
            <word>suggests</word>
            <lemma>suggest</lemma>
            <CharacterOffsetBegin>1627</CharacterOffsetBegin>
            <CharacterOffsetEnd>1635</CharacterOffsetEnd>
            <POS>VBZ</POS>
            <NER>O</NER>
          </token>
          <token id="3">
            <word>that</word>
            <lemma>that</lemma>
            <CharacterOffsetBegin>1636</CharacterOffsetBegin>
            <CharacterOffsetEnd>1640</CharacterOffsetEnd>
            <POS>IN</POS>
            <NER>O</NER>
          </token>
          <token id="4">
            <word>the</word>
            <lemma>the</lemma>
            <CharacterOffsetBegin>1641</CharacterOffsetBegin>
            <CharacterOffsetEnd>1644</CharacterOffsetEnd>
            <POS>DT</POS>
            <NER>O</NER>
          </token>
          <token id="5">
            <word>light</word>
            <lemma>light</lemma>
            <CharacterOffsetBegin>1645</CharacterOffsetBegin>
            <CharacterOffsetEnd>1650</CharacterOffsetEnd>
            <POS>NN</POS>
            <NER>O</NER>
          </token>
          <token id="6">
            <word>could</word>
            <lemma>could</lemma>
            <CharacterOffsetBegin>1651</CharacterOffsetBegin>
            <CharacterOffsetEnd>1656</CharacterOffsetEnd>
            <POS>MD</POS>
            <NER>O</NER>
          </token>
          <token id="7">
            <word>be</word>
            <lemma>be</lemma>
            <CharacterOffsetBegin>1657</CharacterOffsetBegin>
            <CharacterOffsetEnd>1659</CharacterOffsetEnd>
            <POS>VB</POS>
            <NER>O</NER>
          </token>
          <token id="8">
            <word>electrically</word>
            <lemma>electrically</lemma>
            <CharacterOffsetBegin>1660</CharacterOffsetBegin>
            <CharacterOffsetEnd>1672</CharacterOffsetEnd>
            <POS>RB</POS>
            <NER>O</NER>
          </token>
          <token id="9">
            <word>tunable</word>
            <lemma>tunable</lemma>
            <CharacterOffsetBegin>1673</CharacterOffsetBegin>
            <CharacterOffsetEnd>1680</CharacterOffsetEnd>
            <POS>JJ</POS>
            <NER>O</NER>
          </token>
          <token id="10">
            <word>,</word>
            <lemma>,</lemma>
            <CharacterOffsetBegin>1680</CharacterOffsetBegin>
            <CharacterOffsetEnd>1681</CharacterOffsetEnd>
            <POS>,</POS>
            <NER>O</NER>
          </token>
          <token id="11">
            <word>leading</word>
            <lemma>lead</lemma>
            <CharacterOffsetBegin>1682</CharacterOffsetBegin>
            <CharacterOffsetEnd>1689</CharacterOffsetEnd>
            <POS>VBG</POS>
            <NER>O</NER>
          </token>
          <token id="12">
            <word>to</word>
            <lemma>to</lemma>
            <CharacterOffsetBegin>1690</CharacterOffsetBegin>
            <CharacterOffsetEnd>1692</CharacterOffsetEnd>
            <POS>TO</POS>
            <NER>O</NER>
          </token>
          <token id="13">
            <word>switching</word>
            <lemma>switch</lemma>
            <CharacterOffsetBegin>1693</CharacterOffsetBegin>
            <CharacterOffsetEnd>1702</CharacterOffsetEnd>
            <POS>VBG</POS>
            <NER>O</NER>
          </token>
          <token id="14">
            <word>times</word>
            <lemma>time</lemma>
            <CharacterOffsetBegin>1703</CharacterOffsetBegin>
            <CharacterOffsetEnd>1708</CharacterOffsetEnd>
            <POS>NNS</POS>
            <NER>O</NER>
          </token>
          <token id="15">
            <word>of</word>
            <lemma>of</lemma>
            <CharacterOffsetBegin>1709</CharacterOffsetBegin>
            <CharacterOffsetEnd>1711</CharacterOffsetEnd>
            <POS>IN</POS>
            <NER>O</NER>
          </token>
          <token id="16">
            <word>less</word>
            <lemma>less</lemma>
            <CharacterOffsetBegin>1712</CharacterOffsetBegin>
            <CharacterOffsetEnd>1716</CharacterOffsetEnd>
            <POS>JJR</POS>
            <NER>O</NER>
          </token>
          <token id="17">
            <word>than</word>
            <lemma>than</lemma>
            <CharacterOffsetBegin>1717</CharacterOffsetBegin>
            <CharacterOffsetEnd>1721</CharacterOffsetEnd>
            <POS>IN</POS>
            <NER>O</NER>
          </token>
          <token id="18">
            <word>a</word>
            <lemma>a</lemma>
            <CharacterOffsetBegin>1722</CharacterOffsetBegin>
            <CharacterOffsetEnd>1723</CharacterOffsetEnd>
            <POS>DT</POS>
            <NER>O</NER>
          </token>
          <token id="19">
            <word>picosecond</word>
            <lemma>picosecond</lemma>
            <CharacterOffsetBegin>1724</CharacterOffsetBegin>
            <CharacterOffsetEnd>1734</CharacterOffsetEnd>
            <POS>NN</POS>
            <NER>O</NER>
          </token>
          <token id="20">
            <word>.</word>
            <lemma>.</lemma>
            <CharacterOffsetBegin>1734</CharacterOffsetBegin>
            <CharacterOffsetEnd>1735</CharacterOffsetEnd>
            <POS>.</POS>
            <NER>O</NER>
          </token>
        </tokens>
      </sentence>
      <sentence id="11">
        <tokens>
          <token id="1">
            <word>The</word>
            <lemma>the</lemma>
            <CharacterOffsetBegin>1736</CharacterOffsetBegin>
            <CharacterOffsetEnd>1739</CharacterOffsetEnd>
            <POS>DT</POS>
            <NER>O</NER>
          </token>
          <token id="2">
            <word>work</word>
            <lemma>work</lemma>
            <CharacterOffsetBegin>1740</CharacterOffsetBegin>
            <CharacterOffsetEnd>1744</CharacterOffsetEnd>
            <POS>NN</POS>
            <NER>O</NER>
          </token>
          <token id="3">
            <word>,</word>
            <lemma>,</lemma>
            <CharacterOffsetBegin>1744</CharacterOffsetBegin>
            <CharacterOffsetEnd>1745</CharacterOffsetEnd>
            <POS>,</POS>
            <NER>O</NER>
          </token>
          <token id="4">
            <word>along</word>
            <lemma>along</lemma>
            <CharacterOffsetBegin>1746</CharacterOffsetBegin>
            <CharacterOffsetEnd>1751</CharacterOffsetEnd>
            <POS>IN</POS>
            <NER>O</NER>
          </token>
          <token id="5">
            <word>with</word>
            <lemma>with</lemma>
            <CharacterOffsetBegin>1752</CharacterOffsetBegin>
            <CharacterOffsetEnd>1756</CharacterOffsetEnd>
            <POS>IN</POS>
            <NER>O</NER>
          </token>
          <token id="6">
            <word>similar</word>
            <lemma>similar</lemma>
            <CharacterOffsetBegin>1757</CharacterOffsetBegin>
            <CharacterOffsetEnd>1764</CharacterOffsetEnd>
            <POS>JJ</POS>
            <NER>O</NER>
          </token>
          <token id="7">
            <word>research</word>
            <lemma>research</lemma>
            <CharacterOffsetBegin>1765</CharacterOffsetBegin>
            <CharacterOffsetEnd>1773</CharacterOffsetEnd>
            <POS>NN</POS>
            <NER>O</NER>
          </token>
          <token id="8">
            <word>from</word>
            <lemma>from</lemma>
            <CharacterOffsetBegin>1774</CharacterOffsetBegin>
            <CharacterOffsetEnd>1778</CharacterOffsetEnd>
            <POS>IN</POS>
            <NER>O</NER>
          </token>
          <token id="9">
            <word>a</word>
            <lemma>a</lemma>
            <CharacterOffsetBegin>1779</CharacterOffsetBegin>
            <CharacterOffsetEnd>1780</CharacterOffsetEnd>
            <POS>DT</POS>
            <NER>O</NER>
          </token>
          <token id="10">
            <word>Spanish</word>
            <lemma>spanish</lemma>
            <CharacterOffsetBegin>1781</CharacterOffsetBegin>
            <CharacterOffsetEnd>1788</CharacterOffsetEnd>
            <POS>JJ</POS>
            <NER>LOCATION</NER>
          </token>
          <token id="11">
            <word>group</word>
            <lemma>group</lemma>
            <CharacterOffsetBegin>1789</CharacterOffsetBegin>
            <CharacterOffsetEnd>1794</CharacterOffsetEnd>
            <POS>NN</POS>
            <NER>O</NER>
          </token>
          <token id="12">
            <word>,</word>
            <lemma>,</lemma>
            <CharacterOffsetBegin>1794</CharacterOffsetBegin>
            <CharacterOffsetEnd>1795</CharacterOffsetEnd>
            <POS>,</POS>
            <NER>O</NER>
          </token>
          <token id="13">
            <word>appears</word>
            <lemma>appear</lemma>
            <CharacterOffsetBegin>1796</CharacterOffsetBegin>
            <CharacterOffsetEnd>1803</CharacterOffsetEnd>
            <POS>VBZ</POS>
            <NER>O</NER>
          </token>
          <token id="14">
            <word>in</word>
            <lemma>in</lemma>
            <CharacterOffsetBegin>1804</CharacterOffsetBegin>
            <CharacterOffsetEnd>1806</CharacterOffsetEnd>
            <POS>IN</POS>
            <NER>O</NER>
          </token>
          <token id="15">
            <word>the</word>
            <lemma>the</lemma>
            <CharacterOffsetBegin>1807</CharacterOffsetBegin>
            <CharacterOffsetEnd>1810</CharacterOffsetEnd>
            <POS>DT</POS>
            <NER>O</NER>
          </token>
          <token id="16">
            <word>current</word>
            <lemma>current</lemma>
            <CharacterOffsetBegin>1811</CharacterOffsetBegin>
            <CharacterOffsetEnd>1818</CharacterOffsetEnd>
            <POS>JJ</POS>
            <NER>DATE</NER>
            <NormalizedNER>PRESENT_REF</NormalizedNER>
            <Timex tid="t2" type="DATE">PRESENT_REF</Timex>
          </token>
          <token id="17">
            <word>issue</word>
            <lemma>issue</lemma>
            <CharacterOffsetBegin>1819</CharacterOffsetBegin>
            <CharacterOffsetEnd>1824</CharacterOffsetEnd>
            <POS>NN</POS>
            <NER>O</NER>
          </token>
          <token id="18">
            <word>of</word>
            <lemma>of</lemma>
            <CharacterOffsetBegin>1825</CharacterOffsetBegin>
            <CharacterOffsetEnd>1827</CharacterOffsetEnd>
            <POS>IN</POS>
            <NER>O</NER>
          </token>
          <token id="19">
            <word>the</word>
            <lemma>the</lemma>
            <CharacterOffsetBegin>1828</CharacterOffsetBegin>
            <CharacterOffsetEnd>1831</CharacterOffsetEnd>
            <POS>DT</POS>
            <NER>O</NER>
          </token>
          <token id="20">
            <word>journal</word>
            <lemma>journal</lemma>
            <CharacterOffsetBegin>1832</CharacterOffsetBegin>
            <CharacterOffsetEnd>1839</CharacterOffsetEnd>
            <POS>NN</POS>
            <NER>O</NER>
          </token>
          <token id="21">
            <word>Nature</word>
            <lemma>Nature</lemma>
            <CharacterOffsetBegin>1840</CharacterOffsetBegin>
            <CharacterOffsetEnd>1846</CharacterOffsetEnd>
            <POS>NNP</POS>
            <NER>O</NER>
          </token>
          <token id="22">
            <word>.</word>
            <lemma>.</lemma>
            <CharacterOffsetBegin>1846</CharacterOffsetBegin>
            <CharacterOffsetEnd>1847</CharacterOffsetEnd>
            <POS>.</POS>
            <NER>O</NER>
          </token>
        </tokens>
      </sentence>
    </sentences>
  </document>
</root>
